pyngclient/__init__.py
pyngclient/generic_ping_client.py
pyngclient-0.0.3.dist-info/LICENSE
pyngclient-0.0.3.dist-info/METADATA
pyngclient-0.0.3.dist-info/WHEEL
pyngclient-0.0.3.dist-info/top_level.txt
pyngclient-0.0.3.dist-info/RECORD
