Metadata-Version: 2.1
Name: pyngclient
Version: 0.0.3
Summary: PyngClient to MonitoringService
Home-page: https://github.com/Connecterra/PyngClient
Author: Connecterra B.V. (Igor Schouten)
Author-email: igors@connecterra.io
License: GPLv3
Keywords: Monitoring
Platform: UNKNOWN
Classifier: Development Status :: 3 - Alpha
Classifier: Intended Audience :: Developers
Classifier: Topic :: Software Development :: Build Tools
Classifier: License :: OSI Approved :: GNU General Public License v3 (GPLv3)
Classifier: Programming Language :: Python :: 3.6
Classifier: Programming Language :: Python :: 3.7
Classifier: Programming Language :: Python :: 3.8
Classifier: Programming Language :: Python :: 3.9
Requires-Dist: requests
Requires-Dist: isodate
